apicadabri/__init__.py
apicadabri/py.typed
apicadabri-0.5.1.dist-info/METADATA
apicadabri-0.5.1.dist-info/WHEEL
apicadabri-0.5.1.dist-info/licenses/LICENSE
apicadabri-0.5.1.dist-info/RECORD
