Metadata-Version: 2.4
Name: apicadabri
Version: 0.5.1
Summary: Magical tools to interact with web APIs from a data scientist's perspective.
Project-URL: Homepage, https://github.com/CSchoel/apicadabri
Project-URL: Repository, https://github.com/CSchoel/apicadabri
Project-URL: Issues, https://github.com/CSchoel/apicadabri/issues
Project-URL: Changelog, https://github.com/CSchoel/apicadabri/CHANGELOG.md
Author-email: Christopher Schölzel <christopher.schoelzel@mailbox.org>
License-Expression: MIT
License-File: LICENSE
Keywords: API,HTTP,REST,async,batch,data science,fast,parallel
Classifier: Development Status :: 3 - Alpha
Classifier: Framework :: AsyncIO
Classifier: Framework :: Pydantic
Classifier: Framework :: aiohttp
Classifier: Intended Audience :: Developers
Classifier: License :: OSI Approved :: MIT License
Classifier: Programming Language :: Python :: 3
Classifier: Programming Language :: Python :: 3.11
Classifier: Programming Language :: Python :: 3.12
Classifier: Programming Language :: Python :: 3.13
Classifier: Topic :: Internet :: WWW/HTTP
Requires-Python: >=3.11
Requires-Dist: aiohttp>=3.11.14
Requires-Dist: asyncio>=3.4.3
Requires-Dist: humanize>=4.12.3
Requires-Dist: multidict>=6.2.0
Requires-Dist: pydantic>=2.10.6
Requires-Dist: tqdm>=4.67.1
Requires-Dist: yarl>=1.18.3
